plserver/__init__.py
plserver/__main__.py
plserver/file_handler.py
plserver/help.txt
plserver/server.py
plserver/websocket.js
plserver/websocket_handler.py
plserver-1.0.0.dist-info/METADATA
plserver-1.0.0.dist-info/WHEEL
plserver-1.0.0.dist-info/top_level.txt
plserver-1.0.0.dist-info/RECORD
