Metadata-Version: 2.1
Name: plserver
Version: 1.0.0
Summary: Python Live Server - For instant render on broswer while editing html, css, js.
Home-page: https://github.com/o-opeyemi/plserver
Author: Opeyemi Ogunsanya
Author-email: ogunsanyaopeyemi4@gmail.com
License: MIT
Project-URL: Homepage, https://github.com/o-opeyemi/plserver
Project-URL: Tracker, https://github.com/o-opeyemi/plserver/issues
Keywords: plserver,Python Live Server
Classifier: License :: OSI Approved :: MIT License
Classifier: Operating System :: OS Independent
Classifier: Development Status :: 5 - Production/Stable
Classifier: Environment :: Web Environment
Classifier: Intended Audience :: Developers
Classifier: License :: OSI Approved :: MIT License
Classifier: Operating System :: OS Independent
Classifier: Programming Language :: Python
Classifier: Programming Language :: Python :: 3
Classifier: Programming Language :: Python :: 3.8
Classifier: Programming Language :: Python :: 3.9
Classifier: Programming Language :: Python :: 3.10
Classifier: Programming Language :: Python :: 3.11
Requires-Dist: aiohttp (==3.8.4)
Requires-Dist: aiosignal (==1.3.1)
Requires-Dist: async-timeout (==4.0.2)
Requires-Dist: attrs (==22.2.0)
Requires-Dist: certifi (==2022.12.7)
Requires-Dist: charset-normalizer (==3.1.0)
Requires-Dist: frozenlist (==1.3.3)
Requires-Dist: idna (==3.4)
Requires-Dist: multidict (==6.0.4)
Requires-Dist: urllib3 (==1.26.15)
Requires-Dist: yarl (==1.8.2)
